README
setup.py
hatom2atom/__init__.py
hatom2atom/h2aproxy.py
hatom2atom/settings.py
hatom2atom/util.py
hatom2atom.egg-info/PKG-INFO
hatom2atom.egg-info/SOURCES.txt
hatom2atom.egg-info/dependency_links.txt
hatom2atom.egg-info/entry_points.txt
hatom2atom.egg-info/requires.txt
hatom2atom.egg-info/top_level.txt