Metadata-Version: 1.0
Name: hatom2atom
Version: 0.6
Summary: WSGI proxy for transforming hAtom to Atom via hAtom2Atom.xsl.
Home-page: http://lukearno.com/projects/hatom2atom
Author: Luke Arno
Author-email: luke.arno@gmail.com
License: GPL2
Keywords: xml html micorformats atom hatom wsgi proxy
Platform: UNKNOWN
Classifier: Development Status :: 3 - Alpha
Classifier: Environment :: Web Environment
Classifier: Intended Audience :: Developers
Classifier: License :: OSI Approved :: GNU General Public License (GPL)
Classifier: Natural Language :: English
Classifier: Operating System :: OS Independent
Classifier: Programming Language :: Python
Classifier: Topic :: Internet :: WWW/HTTP
Classifier: Topic :: Text Processing :: Markup :: XML
Classifier: Topic :: Text Processing :: Markup :: HTML
